conda_spawn/__init__.py
conda_spawn/_version.py
conda_spawn/activate.py
conda_spawn/cli.py
conda_spawn/exceptions.py
conda_spawn/main.py
conda_spawn/plugin.py
conda_spawn/shell.py
conda_spawn-0.0.4.dist-info/METADATA
conda_spawn-0.0.4.dist-info/WHEEL
conda_spawn-0.0.4.dist-info/entry_points.txt
conda_spawn-0.0.4.dist-info/licenses/LICENSE
conda_spawn-0.0.4.dist-info/RECORD
