Metadata-Version: 2.4
Name: conda-spawn
Version: 0.0.4
Summary: Activate conda environments in new shell processes.
Project-URL: homepage, https://github.com/conda-incubator/conda-spawn
Author-email: Jaime Rodríguez-Guerra <jrodriguez@quansight.com>
License: MIT License
License-File: LICENSE
Classifier: License :: OSI Approved :: BSD License
Classifier: Programming Language :: Python :: 3
Classifier: Programming Language :: Python :: 3 :: Only
Classifier: Programming Language :: Python :: 3.9
Classifier: Programming Language :: Python :: 3.10
Classifier: Programming Language :: Python :: 3.11
Classifier: Programming Language :: Python :: 3.12
Classifier: Programming Language :: Python :: Implementation :: CPython
Classifier: Programming Language :: Python :: Implementation :: PyPy
Requires-Python: >=3.9
Requires-Dist: pexpect
Requires-Dist: shellingham
